blazestore/__init__.py
blazestore/database.py
blazestore/parse.py
blazestore/expr_db/__init__.py
blazestore/expr_db/errors.py
blazestore/expr_db/expr.py
blazestore/expr_db/qdf.py
blazestore/expr_db/udf/__init__.py
blazestore/expr_db/udf/base_udf.py
blazestore/expr_db/udf/cs_udf.py
blazestore/expr_db/udf/d_udf.py
blazestore/expr_db/udf/ind_udf.py
blazestore/expr_db/udf/ts_udf.py
blazestore/factor/__init__.py
blazestore/factor/core.py
blazestore/factor/errors.py
blazestore/updater/__init__.py
blazestore/updater/base.py
blazestore/updater/updater.py
blazestore-0.1.7.dist-info/licenses/LICENSE
blazestore-0.1.7.dist-info/METADATA
blazestore-0.1.7.dist-info/WHEEL
blazestore-0.1.7.dist-info/top_level.txt
blazestore-0.1.7.dist-info/RECORD
