Metadata-Version: 2.4
Name: blazestore
Version: 0.1.7
Summary: The blazing-fast data toolkit for quantitative workflows
License-Expression: MIT
Project-URL: homepage, https://github.com/link-yundi/blazestore
Project-URL: repository, https://github.com/link-yundi/blazestore
Requires-Python: >=3.12
License-File: LICENSE
Requires-Dist: clickhouse-df>=0.1.5
Requires-Dist: connectorx>=0.4.3
Requires-Dist: dynaconf>=3.2.11
Requires-Dist: lark>=1.2.2
Requires-Dist: polars>=1.30.0
Requires-Dist: rich>=14.0.0
Requires-Dist: sqlparse>=0.5.3
Requires-Dist: toolz>=1.0.0
Requires-Dist: varname>=0.14.0
Requires-Dist: xcals>=0.0.3
Requires-Dist: ygo>=1.1.0
Dynamic: license-file
